setup.py
mlend_distributions/Binomialdistribution.py
mlend_distributions/Gaussiandistribution.py
mlend_distributions/Generaldistribution.py
mlend_distributions/__init__.py
mlend_distributions.egg-info/PKG-INFO
mlend_distributions.egg-info/SOURCES.txt
mlend_distributions.egg-info/dependency_links.txt
mlend_distributions.egg-info/not-zip-safe
mlend_distributions.egg-info/top_level.txt