Metadata-Version: 1.0
Name: mlend-distributions
Version: 1.0
Summary: Gaussian distributions
Home-page: UNKNOWN
Author: Dhruv Patel
Author-email: UNKNOWN
License: UNKNOWN
Platform: UNKNOWN
